{
  "李泽儒": {
    "name": "李泽儒",
    "sex": "男",
    "student_id": "23313091",
    "college": "管理学院",
    "is_staying_at_venue": true,
    "registered_events": [
      {
        "event_type": "男子双打",
        "partner": "陈俊杰",
        "is_seed": true
      }
    ]
  },
  "徐跃之": {
    "name": "徐跃之",
    "sex": "男",
    "student_id": "23213422",
    "college": "海洋科学学院",
    "is_staying_at_venue": true,
    "registered_events": [
      {
        "event_type": "男子双打",
        "partner": "周君耀",
        "is_seed": true
      }
    ]
  },
  "赵旭彤": {
    "name": "赵旭彤",
    "sex": "女",
    "student_id": "23357076",
    "college": "中文系珠海",
    "is_staying_at_venue": true,
    "registered_events": [
      {
        "event_type": "混合双打",
        "partner": "许伟",
        "is_seed": true
      },
      {
        "event_type": "女子双打",
        "partner": "麦穗湘",
        "is_seed": true
      },
      {
        "event_type": "女子单打",
        "partner": "",
        "is_seed": true
      }
    ]
  },
  "卓志泳": {
    "name": "卓志泳",
    "sex": "男",
    "student_id": "21308353",
    "college": "中山医学院",
    "is_staying_at_venue": false,
    "registered_events": [
      {
        "event_type": "混合双打",
        "partner": "左黛慧",
        "is_seed": true
      },
      {
        "event_type": "男子单打",
        "partner": "",
        "is_seed": true
      }
    ]
  },
  "廖小鑫": {
    "name": "廖小鑫",
    "sex": "男",
    "student_id": "23111356",
    "college": "人工智能学院",
    "is_staying_at_venue": true,
    "registered_events": [
      {
        "event_type": "男子双打",
        "partner": "高铉清",
        "is_seed": true
      }
    ]
  },
  "梁骜群": {
    "name": "梁骜群",
    "sex": "男",
    "student_id": "25215674",
    "college": "航空航天",
    "is_staying_at_venue": false,
    "registered_events": [
      {
        "event_type": "男子单打",
        "partner": "",
        "is_seed": true
      }
    ]
  },
  "麦穗湘": {
    "name": "麦穗湘",
    "sex": "女",
    "student_id": "23317133",
    "college": "国际金融学院",
    "is_staying_at_venue": true,
    "registered_events": [
      {
        "event_type": "混合双打",
        "partner": "李浩彬",
        "is_seed": true
      },
      {
        "event_type": "女子双打",
        "partner": "赵旭彤",
        "is_seed": true
      },
      {
        "event_type": "女子单打",
        "partner": "",
        "is_seed": true
      }
    ]
  },
  "周君耀": {
    "name": "周君耀",
    "sex": "男",
    "student_id": "25213224",
    "college": "旅游学院",
    "is_staying_at_venue": true,
    "registered_events": [
      {
        "event_type": "男子双打",
        "partner": "徐跃之",
        "is_seed": true
      },
      {
        "event_type": "男子单打",
        "partner": "",
        "is_seed": true
      }
    ]
  },
  "李鸿锋": {
    "name": "李鸿锋",
    "sex": "男",
    "student_id": "25216629",
    "college": "生物医学工程",
    "is_staying_at_venue": false,
    "registered_events": [
      {
        "event_type": "男子单打",
        "partner": "",
        "is_seed": true
      }
    ]
  },
  "李佳伟": {
    "name": "李佳伟",
    "sex": "男",
    "student_id": "22111192",
    "college": "物理与天文学院",
    "is_staying_at_venue": true,
    "registered_events": [
      {
        "event_type": "男子双打",
        "partner": "杜啸颖",
        "is_seed": true
      },
      {
        "event_type": "男子单打",
        "partner": "",
        "is_seed": true
      }
    ]
  },
  "何彦滔": {
    "name": "何彦滔",
    "sex": "男",
    "student_id": "25329006",
    "college": "岭南学院",
    "is_staying_at_venue": false,
    "registered_events": [
      {
        "event_type": "男子单打",
        "partner": "",
        "is_seed": true
      }
    ]
  },
  "杜啸颖": {
    "name": "杜啸颖",
    "sex": "男",
    "student_id": "23111281",
    "college": "物天",
    "is_staying_at_venue": true,
    "registered_events": [
      {
        "event_type": "男子双打",
        "partner": "李佳伟",
        "is_seed": true
      }
    ]
  },
  "刘坤": {
    "name": "刘坤",
    "sex": "男",
    "student_id": "23111336",
    "college": "物理与天文学院",
    "is_staying_at_venue": true,
    "registered_events": [
      {
        "event_type": "男子双打",
        "partner": "马少博",
        "is_seed": true
      },
      {
        "event_type": "男子单打",
        "partner": "",
        "is_seed": true
      }
    ]
  },
  "邓靖陶": {
    "name": "邓靖陶",
    "sex": "男",
    "student_id": "23330020",
    "college": "人工智能学院",
    "is_staying_at_venue": true,
    "registered_events": [
      {
        "event_type": "男子单打",
        "partner": "",
        "is_seed": true
      }
    ]
  },
  "马少博": {
    "name": "马少博",
    "sex": "男",
    "student_id": "25216847",
    "college": "遥感科学与技术学院",
    "is_staying_at_venue": true,
    "registered_events": [
      {
        "event_type": "男子双打",
        "partner": "刘坤",
        "is_seed": true
      },
      {
        "event_type": "男子单打",
        "partner": "",
        "is_seed": true
      }
    ]
  },
  "许伟": {
    "name": "许伟",
    "sex": "男",
    "student_id": "24213183",
    "college": "旅游学院",
    "is_staying_at_venue": true,
    "registered_events": [
      {
        "event_type": "混合双打",
        "partner": "赵旭彤",
        "is_seed": true
      },
      {
        "event_type": "男子双打",
        "partner": "蔡雍",
        "is_seed": true
      },
      {
        "event_type": "男子单打",
        "partner": "",
        "is_seed": true
      }
    ]
  },
  "何晖昶": {
    "name": "何晖昶",
    "sex": "男",
    "student_id": "24217665",
    "college": "中山医学院",
    "is_staying_at_venue": false,
    "registered_events": [
      {
        "event_type": "男子单打",
        "partner": "",
        "is_seed": true
      }
    ]
  },
  "黄志旭": {
    "name": "黄志旭",
    "sex": "男",
    "student_id": "24211858",
    "college": "国际翻译学院",
    "is_staying_at_venue": true,
    "registered_events": [
      {
        "event_type": "混合双打",
        "partner": "李盼",
        "is_seed": true
      },
      {
        "event_type": "男子单打",
        "partner": "",
        "is_seed": true
      }
    ]
  },
  "韩桢": {
    "name": "韩桢",
    "sex": "女",
    "student_id": "24318009",
    "college": "软件工程",
    "is_staying_at_venue": true,
    "registered_events": [
      {
        "event_type": "女子单打",
        "partner": "",
        "is_seed": true
      }
    ]
  },
  "符馨尹": {
    "name": "符馨尹",
    "sex": "女",
    "student_id": "24366011",
    "college": "中国语言文学系（珠海）",
    "is_staying_at_venue": true,
    "registered_events": [
      {
        "event_type": "女子双打",
        "partner": "陈欣橦",
        "is_seed": true
      },
      {
        "event_type": "女子单打",
        "partner": "",
        "is_seed": true
      }
    ]
  },
  "刘志钧": {
    "name": "刘志钧",
    "sex": "男",
    "student_id": "23301045",
    "college": "物理学院",
    "is_staying_at_venue": true,
    "registered_events": [
      {
        "event_type": "混合双打",
        "partner": "杨敏行",
        "is_seed": true
      }
    ]
  },
  "赵硕": {
    "name": "赵硕",
    "sex": "男",
    "student_id": "24303088",
    "college": "遥感科学与技术",
    "is_staying_at_venue": true,
    "registered_events": [
      {
        "event_type": "男子双打",
        "partner": "甘翔宇",
        "is_seed": true
      }
    ]
  },
  "陈欣橦": {
    "name": "陈欣橦",
    "sex": "女",
    "student_id": "24329007",
    "college": "历史学系（珠海）",
    "is_staying_at_venue": true,
    "registered_events": [
      {
        "event_type": "女子双打",
        "partner": "符馨尹",
        "is_seed": true
      },
      {
        "event_type": "女子单打",
        "partner": "",
        "is_seed": true
      }
    ]
  },
  "杨敏行": {
    "name": "杨敏行",
    "sex": "女",
    "student_id": "24349085",
    "college": "物理学院",
    "is_staying_at_venue": true,
    "registered_events": [
      {
        "event_type": "混合双打",
        "partner": "刘志钧",
        "is_seed": true
      },
      {
        "event_type": "女子双打",
        "partner": "张艺欣",
        "is_seed": true
      },
      {
        "event_type": "女子单打",
        "partner": "",
        "is_seed": true
      }
    ]
  },
  "徐燕俊": {
    "name": "徐燕俊",
    "sex": "男",
    "student_id": "24218207",
    "college": "医学院",
    "is_staying_at_venue": true,
    "registered_events": [
      {
        "event_type": "男子单打",
        "partner": "",
        "is_seed": true
      }
    ]
  },
  "陈圣科": {
    "name": "陈圣科",
    "sex": "男",
    "student_id": "22342007",
    "college": "微电子",
    "is_staying_at_venue": true,
    "registered_events": [
      {
        "event_type": "男子双打",
        "partner": "李浩彬",
        "is_seed": true
      },
      {
        "event_type": "男子单打",
        "partner": "",
        "is_seed": true
      }
    ]
  },
  "芶誉彰": {
    "name": "芶誉彰",
    "sex": "男",
    "student_id": "24215420",
    "college": "理学院",
    "is_staying_at_venue": false,
    "registered_events": [
      {
        "event_type": "男子单打",
        "partner": "",
        "is_seed": true
      }
    ]
  },
  "左黛慧": {
    "name": "左黛慧",
    "sex": "女",
    "student_id": "21308070",
    "college": "中山医学院",
    "is_staying_at_venue": true,
    "registered_events": [
      {
        "event_type": "混合双打",
        "partner": "卓志泳",
        "is_seed": true
      },
      {
        "event_type": "女子双打",
        "partner": "覃曦",
        "is_seed": true
      },
      {
        "event_type": "女子单打",
        "partner": "",
        "is_seed": true
      }
    ]
  },
  "黄梓淇": {
    "name": "黄梓淇",
    "sex": "女",
    "student_id": "24303022",
    "college": "遥感科学与技术",
    "is_staying_at_venue": true,
    "registered_events": [
      {
        "event_type": "混合双打",
        "partner": "王岱",
        "is_seed": true
      },
      {
        "event_type": "女子单打",
        "partner": "",
        "is_seed": true
      }
    ]
  },
  "王岱": {
    "name": "王岱",
    "sex": "男",
    "student_id": "22344134",
    "college": "物理与天文",
    "is_staying_at_venue": true,
    "registered_events": [
      {
        "event_type": "混合双打",
        "partner": "黄梓淇",
        "is_seed": true
      },
      {
        "event_type": "男子单打",
        "partner": "",
        "is_seed": true
      }
    ]
  },
  "楊晨君": {
    "name": "楊晨君",
    "sex": "男",
    "student_id": "24330111",
    "college": "岭南学院",
    "is_staying_at_venue": true,
    "registered_events": [
      {
        "event_type": "男子单打",
        "partner": "",
        "is_seed": true
      }
    ]
  },
  "叶宇婷": {
    "name": "叶宇婷",
    "sex": "女",
    "student_id": "23347085",
    "college": "药学院（深圳）",
    "is_staying_at_venue": true,
    "registered_events": [
      {
        "event_type": "女子单打",
        "partner": "",
        "is_seed": true
      }
    ]
  },
  "袁致朗": {
    "name": "袁致朗",
    "sex": "男",
    "student_id": "23339138",
    "college": "数学学院（珠海）",
    "is_staying_at_venue": true,
    "registered_events": [
      {
        "event_type": "混合双打",
        "partner": "邱小柔",
        "is_seed": true
      },
      {
        "event_type": "男子双打",
        "partner": "郭泽涛",
        "is_seed": true
      },
      {
        "event_type": "男子单打",
        "partner": "",
        "is_seed": true
      }
    ]
  },
  "李盼": {
    "name": "李盼",
    "sex": "女",
    "student_id": "23322033",
    "college": "化学工程与技术学院",
    "is_staying_at_venue": true,
    "registered_events": [
      {
        "event_type": "混合双打",
        "partner": "黄志旭",
        "is_seed": true
      },
      {
        "event_type": "女子单打",
        "partner": "",
        "is_seed": true
      }
    ]
  },
  "邱小柔": {
    "name": "邱小柔",
    "sex": "女",
    "student_id": "21306069",
    "college": "旅游学院",
    "is_staying_at_venue": true,
    "registered_events": [
      {
        "event_type": "混合双打",
        "partner": "袁致朗",
        "is_seed": true
      },
      {
        "event_type": "女子单打",
        "partner": "",
        "is_seed": true
      }
    ]
  },
  "袁艺": {
    "name": "袁艺",
    "sex": "女",
    "student_id": "22111332",
    "college": "大气科学",
    "is_staying_at_venue": true,
    "registered_events": [
      {
        "event_type": "女子单打",
        "partner": "",
        "is_seed": true
      }
    ]
  },
  "张蔚塬": {
    "name": "张蔚塬",
    "sex": "男",
    "student_id": "23343084",
    "college": "物理学院",
    "is_staying_at_venue": true,
    "registered_events": [
      {
        "event_type": "男子双打",
        "partner": "李云迪",
        "is_seed": true
      },
      {
        "event_type": "男子单打",
        "partner": "",
        "is_seed": true
      }
    ]
  },
  "胡云戈": {
    "name": "胡云戈",
    "sex": "男",
    "student_id": "25215620",
    "college": "航空航天学院",
    "is_staying_at_venue": true,
    "registered_events": [
      {
        "event_type": "混合双打",
        "partner": "刘泽慧",
        "is_seed": true
      },
      {
        "event_type": "男子单打",
        "partner": "",
        "is_seed": true
      }
    ]
  },
  "刘泽慧": {
    "name": "刘泽慧",
    "sex": "女",
    "student_id": "23215319",
    "college": "管理学院（创业学院）",
    "is_staying_at_venue": true,
    "registered_events": [
      {
        "event_type": "混合双打",
        "partner": "胡云戈",
        "is_seed": true
      },
      {
        "event_type": "女子单打",
        "partner": "",
        "is_seed": true
      }
    ]
  },
  "徐菀优": {
    "name": "徐菀优",
    "sex": "女",
    "student_id": "22344160",
    "college": "物理与天文学院",
    "is_staying_at_venue": true,
    "registered_events": [
      {
        "event_type": "女子双打",
        "partner": "李凌珂",
        "is_seed": true
      },
      {
        "event_type": "女子单打",
        "partner": "",
        "is_seed": true
      }
    ]
  },
  "马克": {
    "name": "马克",
    "sex": "男",
    "student_id": "21111505",
    "college": "土木工程学院",
    "is_staying_at_venue": true,
    "registered_events": [
      {
        "event_type": "混合双打",
        "partner": "卢矜灵",
        "is_seed": true
      },
      {
        "event_type": "男子单打",
        "partner": "",
        "is_seed": true
      }
    ]
  },
  "蔡雍": {
    "name": "蔡雍",
    "sex": "男",
    "student_id": "22342002",
    "college": "微电子",
    "is_staying_at_venue": true,
    "registered_events": [
      {
        "event_type": "男子双打",
        "partner": "许伟",
        "is_seed": true
      },
      {
        "event_type": "男子单打",
        "partner": "",
        "is_seed": true
      }
    ]
  },
  "孙明杭": {
    "name": "孙明杭",
    "sex": "男",
    "student_id": "24215653",
    "college": "航空航天学院",
    "is_staying_at_venue": false,
    "registered_events": [
      {
        "event_type": "男子单打",
        "partner": "",
        "is_seed": true
      }
    ]
  },
  "陈俊杰": {
    "name": "陈俊杰",
    "sex": "男",
    "student_id": "23313018",
    "college": "管理学院",
    "is_staying_at_venue": true,
    "registered_events": [
      {
        "event_type": "男子双打",
        "partner": "李泽儒",
        "is_seed": true
      }
    ]
  },
  "李定样": {
    "name": "李定样",
    "sex": "男",
    "student_id": "25215433",
    "college": "集成电路学院",
    "is_staying_at_venue": false,
    "registered_events": [
      {
        "event_type": "男子单打",
        "partner": "",
        "is_seed": true
      }
    ]
  },
  "王子涵": {
    "name": "王子涵",
    "sex": "女",
    "student_id": "24111435",
    "college": "物天",
    "is_staying_at_venue": true,
    "registered_events": [
      {
        "event_type": "混合双打",
        "partner": "孙宇蒙",
        "is_seed": true
      },
      {
        "event_type": "女子单打",
        "partner": "",
        "is_seed": true
      }
    ]
  },
  "高铉清": {
    "name": "高铉清",
    "sex": "男",
    "student_id": "23317051",
    "college": "国际金融学院",
    "is_staying_at_venue": true,
    "registered_events": [
      {
        "event_type": "男子双打",
        "partner": "廖小鑫",
        "is_seed": true
      }
    ]
  },
  "李云迪": {
    "name": "李云迪",
    "sex": "男",
    "student_id": "24345033",
    "college": "智能工程",
    "is_staying_at_venue": false,
    "registered_events": [
      {
        "event_type": "混合双打",
        "partner": "张艺欣",
        "is_seed": true
      },
      {
        "event_type": "男子双打",
        "partner": "张蔚塬",
        "is_seed": true
      },
      {
        "event_type": "男子单打",
        "partner": "",
        "is_seed": true
      }
    ]
  },
  "甘翔宇": {
    "name": "甘翔宇",
    "sex": "男",
    "student_id": "24303014",
    "college": "遥感",
    "is_staying_at_venue": true,
    "registered_events": [
      {
        "event_type": "男子双打",
        "partner": "赵硕",
        "is_seed": true
      }
    ]
  },
  "吕天翔": {
    "name": "吕天翔",
    "sex": "男",
    "student_id": "24214674",
    "college": "物理与天文学院",
    "is_staying_at_venue": true,
    "registered_events": [
      {
        "event_type": "男子单打",
        "partner": "",
        "is_seed": true
      }
    ]
  },
  "房陈家祺": {
    "name": "房陈家祺",
    "sex": "女",
    "student_id": "25304004",
    "college": "大气科学学院",
    "is_staying_at_venue": false,
    "registered_events": [
      {
        "event_type": "混合双打",
        "partner": "陈彦君",
        "is_seed": true
      }
    ]
  },
  "陈彦君": {
    "name": "陈彦君",
    "sex": "女",
    "student_id": "23307009",
    "college": "地球科学与工程学院",
    "is_staying_at_venue": true,
    "registered_events": [
      {
        "event_type": "混合双打",
        "partner": "房陈家祺",
        "is_seed": true
      }
    ]
  },
  "王振佳": {
    "name": "王振佳",
    "sex": "男",
    "student_id": "20111207",
    "college": "物理学院",
    "is_staying_at_venue": false,
    "registered_events": [
      {
        "event_type": "男子单打",
        "partner": "",
        "is_seed": true
      }
    ]
  },
  "孙宇蒙": {
    "name": "孙宇蒙",
    "sex": "男",
    "student_id": "24111447",
    "college": "物理与天文学院",
    "is_staying_at_venue": true,
    "registered_events": [
      {
        "event_type": "混合双打",
        "partner": "王子涵",
        "is_seed": true
      },
      {
        "event_type": "男子双打",
        "partner": "龙青云",
        "is_seed": true
      }
    ]
  },
  "张艺欣": {
    "name": "张艺欣",
    "sex": "女",
    "student_id": "22110107",
    "college": "哲学系",
    "is_staying_at_venue": true,
    "registered_events": [
      {
        "event_type": "混合双打",
        "partner": "李云迪",
        "is_seed": true
      },
      {
        "event_type": "女子双打",
        "partner": "杨敏行",
        "is_seed": true
      },
      {
        "event_type": "女子单打",
        "partner": "",
        "is_seed": true
      }
    ]
  },
  "龙青云": {
    "name": "龙青云",
    "sex": "男",
    "student_id": "23213496",
    "college": "中法核工程与技术学院",
    "is_staying_at_venue": true,
    "registered_events": [
      {
        "event_type": "男子双打",
        "partner": "孙宇蒙",
        "is_seed": true
      }
    ]
  },
  "黄志成": {
    "name": "黄志成",
    "sex": "男",
    "student_id": "24112137",
    "college": "海洋工程与技术学院",
    "is_staying_at_venue": true,
    "registered_events": [
      {
        "event_type": "男子单打",
        "partner": "",
        "is_seed": true
      }
    ]
  },
  "李浩彬": {
    "name": "李浩彬",
    "sex": "男",
    "student_id": "25216775",
    "college": "中山大学微电子科学与技术学院",
    "is_staying_at_venue": true,
    "registered_events": [
      {
        "event_type": "混合双打",
        "partner": "麦穗湘",
        "is_seed": true
      },
      {
        "event_type": "男子双打",
        "partner": "陈圣科",
        "is_seed": true
      },
      {
        "event_type": "男子单打",
        "partner": "",
        "is_seed": true
      }
    ]
  },
  "操越": {
    "name": "操越",
    "sex": "女",
    "student_id": "22349001",
    "college": "艺术学院",
    "is_staying_at_venue": false,
    "registered_events": [
      {
        "event_type": "混合双打",
        "partner": "涂晨曦",
        "is_seed": true
      },
      {
        "event_type": "女子双打",
        "partner": "涂晨曦",
        "is_seed": true
      },
      {
        "event_type": "女子单打",
        "partner": "",
        "is_seed": true
      }
    ]
  },
  "梁雅雯": {
    "name": "梁雅雯",
    "sex": "女",
    "student_id": "24112102",
    "college": "信息工程学院",
    "is_staying_at_venue": false,
    "registered_events": [
      {
        "event_type": "女子单打",
        "partner": "",
        "is_seed": true
      }
    ]
  },
  "李知筱": {
    "name": "李知筱",
    "sex": "女",
    "student_id": "25213347",
    "college": "国际金融学院",
    "is_staying_at_venue": true,
    "registered_events": [
      {
        "event_type": "女子双打",
        "partner": "曾扬",
        "is_seed": true
      },
      {
        "event_type": "女子单打",
        "partner": "",
        "is_seed": true
      }
    ]
  },
  "朱立涛": {
    "name": "朱立涛",
    "sex": "男",
    "student_id": "24362077",
    "college": "管理学院（创业学院）",
    "is_staying_at_venue": false,
    "registered_events": [
      {
        "event_type": "男子单打",
        "partner": "",
        "is_seed": true
      }
    ]
  },
  "黄汉良": {
    "name": "黄汉良",
    "sex": "男",
    "student_id": "24216029",
    "college": "土木工程学院",
    "is_staying_at_venue": true,
    "registered_events": [
      {
        "event_type": "男子单打",
        "partner": "",
        "is_seed": true
      }
    ]
  },
  "梁庭邦": {
    "name": "梁庭邦",
    "sex": "男",
    "student_id": "25214857",
    "college": "人工智能学院",
    "is_staying_at_venue": true,
    "registered_events": [
      {
        "event_type": "男子单打",
        "partner": "",
        "is_seed": true
      }
    ]
  },
  "邹晋": {
    "name": "邹晋",
    "sex": "男",
    "student_id": "22317233",
    "college": "国际金融学院",
    "is_staying_at_venue": true,
    "registered_events": [
      {
        "event_type": "混合双打",
        "partner": "唐果",
        "is_seed": true
      },
      {
        "event_type": "男子双打",
        "partner": "冯梓隽",
        "is_seed": true
      }
    ]
  },
  "冯梓隽": {
    "name": "冯梓隽",
    "sex": "男",
    "student_id": "21308029",
    "college": "光华口腔医学院",
    "is_staying_at_venue": false,
    "registered_events": [
      {
        "event_type": "男子双打",
        "partner": "邹晋",
        "is_seed": true
      }
    ]
  },
  "唐果": {
    "name": "唐果",
    "sex": "女",
    "student_id": "22339099",
    "college": "数学学院（珠海）",
    "is_staying_at_venue": true,
    "registered_events": [
      {
        "event_type": "混合双打",
        "partner": "邹晋",
        "is_seed": true
      }
    ]
  },
  "卢矜灵": {
    "name": "卢矜灵",
    "sex": "女",
    "student_id": "24111298",
    "college": "国际关系学院",
    "is_staying_at_venue": true,
    "registered_events": [
      {
        "event_type": "混合双打",
        "partner": "马克",
        "is_seed": true
      }
    ]
  },
  "涂晨曦": {
    "name": "涂晨曦",
    "sex": "女",
    "student_id": "23315076",
    "college": "国际翻译学院",
    "is_staying_at_venue": true,
    "registered_events": [
      {
        "event_type": "混合双打",
        "partner": "操越",
        "is_seed": true
      },
      {
        "event_type": "女子双打",
        "partner": "操越",
        "is_seed": true
      }
    ]
  },
  "李锐": {
    "name": "李锐",
    "sex": "男",
    "student_id": "22342042",
    "college": "微电子科学与技术学院",
    "is_staying_at_venue": false,
    "registered_events": [
      {
        "event_type": "男子单打",
        "partner": "",
        "is_seed": true
      }
    ]
  },
  "邓博文": {
    "name": "邓博文",
    "sex": "男",
    "student_id": "25322047",
    "college": "化学学院",
    "is_staying_at_venue": false,
    "registered_events": [
      {
        "event_type": "男子单打",
        "partner": "",
        "is_seed": true
      }
    ]
  },
  "曾扬": {
    "name": "曾扬",
    "sex": "女",
    "student_id": "24213551",
    "college": "中法核工程与技术学院",
    "is_staying_at_venue": true,
    "registered_events": [
      {
        "event_type": "女子双打",
        "partner": "李知筱",
        "is_seed": true
      }
    ]
  },
  "李凌珂": {
    "name": "李凌珂",
    "sex": "女",
    "student_id": "23214936",
    "college": "大气科学学院",
    "is_staying_at_venue": true,
    "registered_events": [
      {
        "event_type": "女子双打",
        "partner": "徐菀优",
        "is_seed": true
      }
    ]
  },
  "胡静怡": {
    "name": "胡静怡",
    "sex": "女",
    "student_id": "24316051",
    "college": "国际金融学院",
    "is_staying_at_venue": true,
    "registered_events": [
      {
        "event_type": "女子双打",
        "partner": "李嘉仪",
        "is_seed": true
      }
    ]
  },
  "李嘉仪": {
    "name": "李嘉仪",
    "sex": "女",
    "student_id": "24361033",
    "college": "哲学系（珠海）",
    "is_staying_at_venue": true,
    "registered_events": [
      {
        "event_type": "女子双打",
        "partner": "胡静怡",
        "is_seed": true
      }
    ]
  },
  "覃曦": {
    "name": "覃曦",
    "sex": "女",
    "student_id": "24112800",
    "college": "中山眼科中心",
    "is_staying_at_venue": false,
    "registered_events": [
      {
        "event_type": "女子双打",
        "partner": "左黛慧",
        "is_seed": true
      }
    ]
  },
  "梁梓聪": {
    "name": "梁梓聪",
    "sex": "男",
    "student_id": "25346065",
    "college": "微电子科学与技术学院",
    "is_staying_at_venue": true,
    "registered_events": [
      {
        "event_type": "男子单打",
        "partner": "",
        "is_seed": true
      }
    ]
  },
  "郭泽涛": {
    "name": "郭泽涛",
    "sex": "男",
    "student_id": "22330026",
    "college": "人工智能院",
    "is_staying_at_venue": true,
    "registered_events": [
      {
        "event_type": "男子双打",
        "partner": "袁致朗",
        "is_seed": true
      }
    ]
  }
}